{
  "project_info": {
    "project_number": "792265527658",
    "project_id": "databasebsp-4f106",
    "storage_bucket": "databasebsp-4f106.appspot.com"
  },
  "client": [
    {
      "client_info": {
        "mobilesdk_app_id": "1:792265527658:android:99b9ade21dad0dd022d513",
        "android_client_info": {
          "package_name": "com.example.adminbsp"
        }
      },
      "oauth_client": [],
      "api_key": [
        {
          "current_key": "AIzaSyA30XuzFmPbfg6lWXP0ggKDcdNv23LT4B0"
        }
      ],
      "services": {
        "appinvite_service": {
          "other_platform_oauth_client": []
        }
      }
    },
    {
      "client_info": {
        "mobilesdk_app_id": "1:792265527658:android:57b9e43182c2baa922d513",
        "android_client_info": {
          "package_name": "com.example.mainappbsp"
        }
      },
      "oauth_client": [],
      "api_key": [
        {
          "current_key": "AIzaSyA30XuzFmPbfg6lWXP0ggKDcdNv23LT4B0"
        }
      ],
      "services": {
        "appinvite_service": {
          "other_platform_oauth_client": []
        }
      }
    }
  ],
  "configuration_version": "1"
}